nicolasflamel/__init__.py
nicolasflamel/mwc_pay.py
nicolasflamel.mwc_pay-0.2.0.dist-info/LICENSE
nicolasflamel.mwc_pay-0.2.0.dist-info/METADATA
nicolasflamel.mwc_pay-0.2.0.dist-info/WHEEL
nicolasflamel.mwc_pay-0.2.0.dist-info/top_level.txt
nicolasflamel.mwc_pay-0.2.0.dist-info/RECORD
