Metadata-Version: 2.1
Name: nicolasflamel.mwc-pay
Version: 0.2.0
Summary: Python SDK for MWC Pay
Author: Nicolas Flamel
License: MIT License
Project-URL: Homepage, https://github.com/NicolasFlamel1/MWC-Pay-Python-SDK
Project-URL: Issues, https://github.com/NicolasFlamel1/MWC-Pay-Python-SDK/issues
Keywords: MWC Pay,MWC,MimbleWimble Coin,Mimblewimble,Payment Processor,Cryptocurrency,Crypto
Classifier: Programming Language :: Python :: 3
Classifier: License :: OSI Approved :: MIT License
Classifier: Operating System :: OS Independent
Requires-Python: >=3.8
License-File: LICENSE
